[
	{
		"branchId": 1,
		"name": "Makro Yunusobod",
		"address": "Yunusuobod, Shahristanskiy",
		"marketId": 1
	},
	{
		"branchId": 2,
		"name": "Makro Chimboy",
		"address": "Chimboy, Markaz",
		"marketId": 1
	},
	{
		"branchId": 3,
		"name": "Karzika chilonzor",
		"address": "Yunusuobod, Chilonzor metro",
		"marketId": 2
	},
	{
		"branchId": 4,
		"name": "Look Shuhrat",
		"address": "Qatortol, Chilonzor metro",
		"marketId": 4
	},
	{
		"branchId": 5,
		"name": "Makro Yunusobod",
		"address": "Yunusobod",
		"marketId": 2
	}
]
